wpi
wpi2exe
