Metadata-Version: 1.1
Name: wpi
Version: 0.10.2
Summary: Windows Printer Installer
Home-page: https://github.com/meng89/wpi
Author: Chen Meng
Author-email: ObserverChan@gmail.com
License: LGPL
Platform: UNKNOWN
Classifier: Intended Audience :: Developers
Classifier: Intended Audience :: Information Technology
Classifier: Intended Audience :: System Administrators
Classifier: License :: OSI Approved :: GNU Library or Lesser General Public License (LGPL)
Classifier: Operating System :: Microsoft :: Windows
Classifier: Programming Language :: Python :: 3
Classifier: Topic :: Software Development :: Libraries :: Python Modules
